nwnsdk/__init__.py
nwnsdk/app_logging.py
nwnsdk/config.py
nwnsdk/nwn_client.py
nwnsdk/postgres/__init__.py
nwnsdk/postgres/database.py
nwnsdk/postgres/dbmodels.py
nwnsdk/postgres/postgres_client.py
nwnsdk/rabbitmq/__init__.py
nwnsdk/rabbitmq/rabbitmq_client.py
nwnsdk-0.0.12.dist-info/LICENSE
nwnsdk-0.0.12.dist-info/METADATA
nwnsdk-0.0.12.dist-info/WHEEL
nwnsdk-0.0.12.dist-info/top_level.txt
nwnsdk-0.0.12.dist-info/RECORD
