Metadata-Version: 2.1
Name: nwnsdk
Version: 0.0.12
Summary: Nieuwe Warmte Nu - compute engine sdk python
Author-email: NieuweWarmteNu <info@nwn.nu>
Project-URL: Homepage, https://github.com/pypa/sampleproject
Project-URL: Bug Tracker, https://github.com/pypa/sampleproject/issues
Classifier: License :: OSI Approved :: GNU General Public License v3 (GPLv3)
Classifier: Programming Language :: Python :: 3
Classifier: Programming Language :: Python :: 3.11
Classifier: Operating System :: OS Independent
Classifier: Development Status :: 3 - Alpha
Classifier: Intended Audience :: Developers
Classifier: Intended Audience :: Science/Research
Classifier: Intended Audience :: Information Technology
Classifier: Topic :: Scientific/Engineering
Classifier: Topic :: Scientific/Engineering :: Mathematics
Classifier: Topic :: Scientific/Engineering :: Physics
Requires-Python: >=3.8
License-File: LICENSE
Requires-Dist: python-dotenv ==1.0.0
Requires-Dist: pika ==1.3.2
Requires-Dist: pika-stubs ==0.1.3
Requires-Dist: SQLAlchemy ==2.0.19
Requires-Dist: sqlalchemy-stubs ==0.4
Requires-Dist: psycopg2-binary ==2.9.7
Provides-Extra: dev
Requires-Dist: setuptools-git-versioning <2 ; extra == 'dev'
Requires-Dist: pip-tools ; extra == 'dev'
Requires-Dist: build ; extra == 'dev'
Requires-Dist: setuptools ; extra == 'dev'
